[
    {
        "currentAge": 40,
        "retirementAge": 68,
        "currentAnnualIncome": 100000,
        "spouseAnnualIncome": 75000,
        "currentRetirementSavings": 500000,
        "currentRetirementContribution": 10,
        "annualContributionIncrease": 1,
        "socialSecurityIncome": true,
        "relationshipStatus": "Married",
        "socialSecurityOverride": 4000,
        "additionalIncome": 500,
        "yearsRetirementNeedsToLast": 20,
        "postRetirementInflation": true,
        "percentFinalIncomeDesired": 75,
        "preRetirementInvestmentReturn": 8,
        "postRetirementInvestmentReturn": 5
    },
    {
        "currentAge": 30,
        "retirementAge": 65,
        "currentAnnualIncome": 80000,
        "spouseAnnualIncome": 0,
        "currentRetirementSavings": 100000,
        "currentRetirementContribution": 15,
        "annualContributionIncrease": 2,
        "socialSecurityIncome": false,
        "relationshipStatus": "Single",
        "socialSecurityOverride": 0,
        "additionalIncome": 0,
        "yearsRetirementNeedsToLast": 25,
        "postRetirementInflation": false,
        "percentFinalIncomeDesired": 80,
        "preRetirementInvestmentReturn": 7,
        "postRetirementInvestmentReturn": 4
    },
    {
        "currentAge": 25,
        "retirementAge": 60,
        "currentAnnualIncome": 55000,
        "spouseAnnualIncome": 45000,
        "currentRetirementSavings": 20000,
        "currentRetirementContribution": 8,
        "annualContributionIncrease": 3,
        "socialSecurityIncome": true,
        "relationshipStatus": "Married",
        "socialSecurityOverride": 2500,
        "additionalIncome": 200,
        "yearsRetirementNeedsToLast": 30,
        "postRetirementInflation": true,
        "percentFinalIncomeDesired": 70,
        "preRetirementInvestmentReturn": 9,
        "postRetirementInvestmentReturn": 6
    },
    {
        "currentAge": 50,
        "retirementAge": 70,
        "currentAnnualIncome": 150000,
        "spouseAnnualIncome": 0,
        "currentRetirementSavings": 800000,
        "currentRetirementContribution": 20,
        "annualContributionIncrease": 1,
        "socialSecurityIncome": false,
        "relationshipStatus": "Single",
        "socialSecurityOverride": 0,
        "additionalIncome": 1000,
        "yearsRetirementNeedsToLast": 15,
        "postRetirementInflation": false,
        "percentFinalIncomeDesired": 90,
        "preRetirementInvestmentReturn": 6,
        "postRetirementInvestmentReturn": 3
    }
]
